{
  "related": {
    "articles" : [
      { "size": "small",
        "flag": {
          "type": "The Code Says",
          "issue": "Sept. 2017"
        },
        "authors": [
          {
            "name" : "Annalise Norling"
          }
        ],
        "title": {
          "href": "#",
          "class": "joe__article-teaser__title",
          "text":"The AMA Code of Medical Ethics’ Opinions Related to Health Care for Incarcerated People"
        }
      },
      {
        "size": "small",
        "flag": {
          "type": "Ethics Case",
          "issue": "Apr. 2017",
          "class": "joe__flag--green"
        },
        "authors": [
          {
            "name" : "Tom Peteet, MD"
          },
          {
            "name" : "Matt Tobey, MD, MPH"
          }
        ],
        "title": {
          "href": "#",
          "class": "joe__article-teaser__title",
          "text":"How Should a Health Care Professional Respond to an Incarcerated Patient’s Request for a Particular Treatment?"
        }
      },
      {
        "size": "small",
        "flag": {
          "type": "Medicine and Society",
          "issue": "Feb. 2017"
        },
        "authors": [
          {
            "name" : "E. Bernadette McKinney, JD, PhD"
          }
        ],
        "title": {
          "href": "#",
          "class": "joe__article-teaser__title",
          "text":"Hard Time and Health Care: The Squeeze on Medicine Behind Bars"
        }
      }
    ]
  }
}
